wikibase_rest_stainless/__init__.py
wikibase_rest_stainless/_base_client.py
wikibase_rest_stainless/_client.py
wikibase_rest_stainless/_compat.py
wikibase_rest_stainless/_constants.py
wikibase_rest_stainless/_exceptions.py
wikibase_rest_stainless/_files.py
wikibase_rest_stainless/_models.py
wikibase_rest_stainless/_qs.py
wikibase_rest_stainless/_resource.py
wikibase_rest_stainless/_response.py
wikibase_rest_stainless/_streaming.py
wikibase_rest_stainless/_types.py
wikibase_rest_stainless/_version.py
wikibase_rest_stainless/py.typed
wikibase_rest_stainless/_utils/__init__.py
wikibase_rest_stainless/_utils/_logs.py
wikibase_rest_stainless/_utils/_proxy.py
wikibase_rest_stainless/_utils/_streams.py
wikibase_rest_stainless/_utils/_sync.py
wikibase_rest_stainless/_utils/_transform.py
wikibase_rest_stainless/_utils/_typing.py
wikibase_rest_stainless/_utils/_utils.py
wikibase_rest_stainless/lib/.keep
wikibase_rest_stainless/resources/__init__.py
wikibase_rest_stainless/resources/openapi.py
wikibase_rest_stainless/resources/property_data_types.py
wikibase_rest_stainless/resources/statements.py
wikibase_rest_stainless/resources/entities/__init__.py
wikibase_rest_stainless/resources/entities/entities.py
wikibase_rest_stainless/resources/entities/items/__init__.py
wikibase_rest_stainless/resources/entities/items/aliases.py
wikibase_rest_stainless/resources/entities/items/descriptions.py
wikibase_rest_stainless/resources/entities/items/items.py
wikibase_rest_stainless/resources/entities/items/labels.py
wikibase_rest_stainless/resources/entities/items/sitelinks.py
wikibase_rest_stainless/resources/entities/items/statements.py
wikibase_rest_stainless/resources/entities/properties/__init__.py
wikibase_rest_stainless/resources/entities/properties/aliases.py
wikibase_rest_stainless/resources/entities/properties/descriptions.py
wikibase_rest_stainless/resources/entities/properties/labels.py
wikibase_rest_stainless/resources/entities/properties/properties.py
wikibase_rest_stainless-0.1.0a1.dist-info/METADATA
wikibase_rest_stainless-0.1.0a1.dist-info/WHEEL
wikibase_rest_stainless-0.1.0a1.dist-info/licenses/LICENSE
wikibase_rest_stainless-0.1.0a1.dist-info/RECORD
